README
setup.py
tiddlywebplugins/__init__.py
tiddlywebplugins/bimport.py
tiddlywebplugins.bimport.egg-info/PKG-INFO
tiddlywebplugins.bimport.egg-info/SOURCES.txt
tiddlywebplugins.bimport.egg-info/dependency_links.txt
tiddlywebplugins.bimport.egg-info/namespace_packages.txt
tiddlywebplugins.bimport.egg-info/requires.txt
tiddlywebplugins.bimport.egg-info/top_level.txt