Metadata-Version: 1.0
Name: tiddlywebplugins.bimport
Version: 0.2
Summary: Import binary content into TiddlyWeb via twanager
Home-page: http://pypi.python.org/pypi/tiddlywebplugins.bimport
Author: Ben Gillies
Author-email: bengillies@gmail.com
License: UNKNOWN
Platform: Posix; MacOS X; Windows
